csv_to_dynamodb/__init__.py
csv_to_dynamodb/csv_to_dynamodb.py
csv_to_dynamodb-0.2.20.dist-info/LICENSE
csv_to_dynamodb-0.2.20.dist-info/METADATA
csv_to_dynamodb-0.2.20.dist-info/WHEEL
csv_to_dynamodb-0.2.20.dist-info/top_level.txt
csv_to_dynamodb-0.2.20.dist-info/RECORD
